{
  "1 . Kto? Co?": "1 . Who? What?",
  "1 stopień- 2 stopnie": "1st degree - 2nd degree",
  "1. Mianownik kto , co": "1. Nominative who, what",
  "10 lat temu": "Ten years ago",
  "100 tysięcy": "100 thousand",
  "11 przypadków": "11 cases",
  "12 ludzi zginęło": "12 people died",
  "15 lat temu ja lubiłem Taylor": "15 years ago I liked Taylor",
  "17 osób": "17 people",
  "2 dni w tygodniu": "2 days a week",
  "2 godziny": "2 hours",
  "2 razy w miesiącu": "2 times a month",
  "2. D-G Kogo ? Czego?": "2. D-G Who? What?",
  "2. dopełniacz kogo, czego": "2. genitive of whom, of what",
  "20 lat temu": "20 years ago",
  "3 lata temu nie mogłem chodzić": "3 years ago I couldn't walk",
  "3 spotkania": "3 meetings",
  "3. Celownik": "3. Crosshair",
  "3. celownik - komu, czemu": "3. dative - to whom, why",
  "4 . Biernik - Kogo? Co?": "4 . Biernik - Whom? What?",
  "4 godziny pociągiem": "4 hours by train",
  "4 lata temu": "4 years ago",
  "4. biernik kogo/ co": "4. accusative case of whom/what",
  "5 chlebów": "5 loaves",
  "5 razy": "5 times",
  "5. N - I - KIm? Czym?": "5. N - I - WHOm? What?",
  "5. Narzędnik kim, czym": "5. A guide to who and what",
  "50 km": "50 km",
  "6 . M- o kim? o czym?": "6 . M-about who? about what?",
  "6. miejscownik o kim, o czym": "6. locative about whom, about what",
  "7. wołacz": "7. vocative",
  "8 lat temu": "8 years ago",
  "Agata intereseuje się pogodą": "Agata is interested in the weather",
  "Agata lubi fotografować samoloty": "Agata likes photographing planes",
  "Agata lubi prysznic": "Agata likes the shower",
  "Agata nic robiła": "Agatha did nothing",
  "Agata nie chodzi na spacer codziennie": "Agata doesn't go for a walk every day",
  "Agata nie lubi Polski": "Agata doesn't like Poland",
  "Agata nie lubi brytyjskich seriali": "Agata doesn't like British TV series",
  "Agata nie robi takich rzeczy": "Agata doesn't do such things",
  "Agata nie zna mojej przyjaciółki": "Agata doesn't know my friend",
  "Agata nigdy nie jeździ rowerem/na rowerze": "Agata never rides a bicycle",
  "Agata nudzi się w Polsce": "Agata is bored in Poland",
  "Agata spała": "Agatha was sleeping",
  "Agata urodziła się w Gdańsku": "Agata was born in Gdańsk",
  "Agata znalazła": "Agatha found it",
  "Ale wstyd!": "What a shame!",
  "Angielskie sporty są popularne": "English sports are popular",
  "Anglia": "England",
  "Anglii": "England",
  "Autobusem jeździ się szybko i tanio": "The bus is fast and cheap",
  "Bardzo mi przykro": "I'm so sorry",
  "Białoruś": "Belarus",
  "Biblia": "Bible",
  "Biernik": "Accusative",
  "Biernik ( Kogo? Co?": "Accusative (Whom? What?",
  "Brat jes starszy": "My brother is older",
  "Brighton jest najpiękniejsze dla mnie": "Brighton is the most beautiful for me",
  "Byliśmy blisko": "We were close",
  "Byłem introwerykiem": "I was an introvert",
  "Byłem zmęczony": "I was tired",
  "Chcę rozumieć matkę Agaty": "I want to understand Agata's mother",
  "Chiny": "China",
  "Chodziliśmy razem ze szkoły": "We walked from school together",
  "Co Pani/ Panu dolega?": "What's wrong with you?",
  "Co robiliście?": "What were you doing?",
  "Co robisz w Nowy Rok": "What are you doing on New Year's Eve?",
  "Co robisz zawodowo?": "What do you do professionally?",
  "Co słychać?": "What's up",
  "Co tam?": "What's up?",
  "Co u Ciebie?": "How are you",
  "Co ubierasz na ślub": "What do you wear to a wedding?",
  "Codziennie było gorąco": "It was hot every day",
  "Czasami ona o tym rozmawia": "Sometimes she talks about it",
  "Czasami pracuję w biurze": "Sometimes I work in the office",
  "Czech - Czeszka": "Czech - Czech woman",
  "Czechy": "The czech republic",
  "Czechy - w Czechach": "Czech Republic - in the Czech Republic",
  "Czego Agata nie lubi w Polsce": "What Agata doesn't like about Poland",
  "Czego nie lubisz jeść?": "What don't you like to eat?",
  "Czy Pani ma prawo jazdy?": "Do you have a driving license?",
  "Czy Pani pali?": "Do you smoke?",
  "Czy kogoś pani szuka?": "Are you looking for someone?",
  "Czy lubi Pani sport?": "Do you like sports?",
  "Czy ma Pani dzieci ?": "Do you have children?",
  "Czy mogę Pani pomóc?": "Can I help you?",
  "Czy ty poszedłeś późno spać w sobotę": "Did you go to bed late on Saturday",
  "Czy wasze koty boją się fajerwerków": "Are your cats afraid of fireworks?",
  "Czym się interesujesz?": "What you're interested?",
  "Często rozmawiamy": "We talk often",
  "Danuta ma około 64": "Danuta is about 64",
  "Dlatego nie chcemy dzieci": "That's why we don't want children",
  "Dzieci nie lubiały muzeum": "The children didn't like the museum",
  "Dziekuje bardzo": "Thank you very much",
  "Dzisiaj zostaję w hotelu": "Today I'm staying at the hotel",
  "Edynburg": "Edinburgh",
  "Europa lub Azja jest dla mnie bardziej interesująca": "Europe or Asia is more interesting to me",
  "Eurowizja": "Eurovision",
  "Ewa powie nam co warto zobaczyć w Warszawie": "Ewa will tell us what is worth seeing in Warsaw",
  "Finlandia": "Finland",
  "Firma dostarczyła zmywarkę wcześniej": "The company delivered the dishwasher earlier",
  "Fracja": "Fraction",
  "Francja": "France",
  "Francja - we Francji": "France - in France",
  "Gdzie grasz?": "Where do you play?",
  "Gdzie pracujesz?": "Where do you work?",
  "Gramy w pubie, w barze": "We play in a pub, in a bar",
  "Grałem na gitarze i na skrzypcach": "I played the guitar and the violin",
  "Grałem w tenisa": "I played tennis",
  "Grecja": "Greece",
  "Hiszpania": "Spain",
  "Homework!": "Homework!",
  "Ich Troje": "Three of them",
  "Idziemy na koncert": "We are going to the concert",
  "Idę na górę": "I'm going upstairs",
  "Ile stron": "How many pages",
  "Interesuje mnie kultura polska": "I am interested in Polish culture",
  "Interesuje mnie muzyka": "I'm interested in music",
  "Interesujący styl": "Interesting style",
  "Irlandia": "Ireland",
  "Ja analizuję jej teksty": "I analyze her texts",
  "Ja budzę się": "I wake up",
  "Ja byłam w Argentynie": "I was in Argentina",
  "Ja chcę spać": "I want to sleep",
  "Ja chodzę chetnie do kina": "I like to go to the cinema",
  "Ja chodzę codziennie na spacer": "I go for a walk every day",
  "Ja gram sam": "I play alone",
  "Ja jadę latem do mojej rodziny": "I'm going to visit my family in the summer",
  "Ja jestem": "I am",
  "Ja lubię zimno": "I like the cold",
  "Ja mam 2 siostrzenice": "I have 2 nieces",
  "Ja mam 3 bratanice": "I have 3 nieces",
  "Ja mam 3 koncerty": "I have 3 concerts",
  "Ja mam bratanka": "I have a nephew",
  "Ja mam więcej przyjaciółek niż przyjaciół": "I have more female friends than male friends",
  "Ja miałem": "I had",
  "Ja mieszkam na jedenastym piętrze": "I live on the eleventh floor",
  "Ja mieszkam na trzecim": "I live on the third floor",
  "Ja muszę skończyć książkę": "I have to finish the book",
  "Ja nie byłem na zakupach": "I wasn't shopping",
  "Ja nie chce pracować": "I don't want to work",
  "Ja nie mógłbym mieszkać w Polsce": "I couldn't live in Poland",
  "Ja nie wiem jaka ta rasa": "I don't know what breed this is",
  "Ja nigdy nie byłem w Warszawie": "I've never been to Warsaw",
  "Ja piekłem chleb": "I baked bread",
  "Ja pojechałem": "I went",
  "Ja poznałem": "I met",
  "Ja pracuję mniej": "I work less",
  "Ja studiowałam na uniwersytecie 15 lat temu": "I studied at university 15 years ago",
  "Ja wolę jeść ser niż szynkę": "I prefer to eat cheese than ham",
  "Ja wspierałem przyjaciół": "I supported my friends",
  "Ja właśnie zjadłam śniadanie": "I just ate breakfast",
  "Ja zawsze w poniedziałek mam spotkanie": "I always have a meeting on Monday",
  "Jak dojechać do centrum?": "How to get to the center?",
  "Jak dojsć do centrum?": "How to get to the center?",
  "Jak idzie?": "How it's going?",
  "Jak masz na imię?": "What's your name?",
  "Jak masz na nazwisko?": "What is your surname?",
  "Jak się Pani / pan czuje": "How are you feeling?",
  "Jak się nazywasz?": "What is your name?",
  "Jaka ona jest": "How is she like",
  "Jaki On jest": "How is he",
  "Jaki dzisiaj jest dzień?": "What day is today?",
  "Jaki jest Pani stan cywilny?": "What is your marital status?",
  "Jaki jest twój adres": "What's your adress",
  "Jaki jest twój numer telefonu?": "What is your phone number?",
  "Jaki język ona zna": "What language does she know?",
  "Jaki rozmiar pani potrzebuje?": "What size do you need?",
  "Jakie ono jest": "What is it like?",
  "Jedliśmy": "We ate",
  "Jedziemy do Warszwy": "We're going to Warsaw",
  "Jego córki są dorosłe": "His daughters are adults",
  "Jego syn jest nastolatkiem": "His son is a teenager",
  "Jej dzieci lubią kupować ubrania": "Her children like to buy clothes",
  "Jest 7th": "It's 7th",
  "Jest brzydko": "It's ugly",
  "Jest mi to obojętne": "I do not care",
  "Jest mleko?": "Is there milk?",
  "Jest poniedziałek": "It's Monday",
  "Jest ważne": "Is important",
  "Jest ładnie": "Its nice",
  "Jestem na górze": "I'm upstairs",
  "Jestem samoukiem": "I am self-taught",
  "Jesteś mężatką?": "Are you married?",
  "Jesteśmy bardzo różni od siebie": "We are very different from each other",
  "Jesteśmy przyjaciółmi ale on nie lubi rozmawiać": "We are friends but he doesn't like to talk",
  "Jesteśmy z innego pokolenia": "We are from a different generation",
  "Jeśli jesteś z tego miejsca": "If you are from here",
  "Jutro lecimy do Londynu": "We're flying to London tomorrow",
  "Jutro muszę zadzwonić do mojej ulubionej przyjaciółki": "Tomorrow I have to call my favorite friend",
  "Kiedy jedziesz do miasto jest łatwo": "When you go to town it's easy",
  "Kiedy jedziesz na wieś to nie jest łatwe": "When you go to the countryside it's not easy",
  "Kiedy miałem 13 lat": "When I was 13 years old",
  "Kiedy piję kawę nie mogę spać": "When I drink coffee I can't sleep",
  "Kiedy przyjechaliście?": "When did you arrive?",
  "Kim jesteś z zawodu?": "What's your occupation?",
  "Kim on jest": "Who is he",
  "Kim ona jest": "Who is she",
  "Kim ono jest": "Who is it?",
  "Klienci są trudni": "Customers are difficult",
  "Krowy muczą": "Cows moo",
  "Kto ? Co?": "Who ? What?",
  "Która jest godzina?": "What time is it?",
  "Lato jest długie": "Summer is long",
  "Litwa": "Lithuania",
  "Lubi ludzi": "He likes people",
  "Lubię czarny": "I like black",
  "Lubię rozmawiać z nim": "I like talking to him",
  "Lubiłem książki": "I liked books",
  "Ludzie sa podobni": "People are similar",
  "Ludzie są mili": "People are nice",
  "Ludzie w Polsce nie pracują w weekendy": "People in Poland don't work on weekends",
  "Mam 12 osób w mojej rodzinie": "I have 12 people in my family",
  "Mam dużo do poprawy": "I have a lot to improve",
  "Mam dwóch trzech przyjaciół": "I have two and three friends",
  "Mam koncert w weekend": "I have a concert this weekend",
  "Mam na nazwisko Lisecka": "My name is Lisecka",
  "Mam nadzieję że nic": "I hope nothing",
  "Mam przyjaciela": "I have a friend",
  "Mam przyjaciół, którzy są ze Słowenii": "I have friends who are from Slovenia",
  "Mam rozmowę o pracę": "I have a job interview",
  "Mam spotkanie w pracy": "I have a meeting at work",
  "Mama Agaty jest aktywna zawodowo": "Agata's mother is professionally active",
  "Mianownik": "Denominator",
  "Miałem dobre oceny": "I had good grades",
  "Mieszkałem znowu": "I lived again",
  "Moi przyjaciele są": "My friends are",
  "Moi przyjeciele": "My friends",
  "Moi rodzice": "My parents",
  "Moi rodzice byli tutaj": "My parents were here",
  "Moja mama coś mówi, a mój tata mówi coś innego": "My mom says something and my dad says something else",
  "Moja mama i tata": "My mom and dad",
  "Moja mama spiewa w kościele": "My mother sings in church",
  "Moja matka ma 74": "My mother is 74",
  "Moja przyjaciółka": "My friend",
  "Moje siostry nie": "My sisters don't",
  "Możemy o tym rozmawiać": "We can talk about it",
  "Muszę zrobić dla niej sklep internetowy": "I need to make an online store for her",
  "My byliśmy razem w muzeum": "We were in the museum together",
  "My byliśmy tam krótko": "We were there for a short time",
  "My będziemy gotować": "We will cook",
  "My będziemy w Warszawie przez tydzień": "We will be in Warsaw for a week",
  "My gotujemy": "We cook",
  "My jesteśmy różni": "We are different",
  "My lubimy podróżować pociągiem": "We like traveling by train",
  "My znamy się od 26 lat": "We have known each other for 26 years",
  "My zostajemy w domu": "We stay at home",
  "Mój brat nie lubi rozmwiać": "My brother doesn't like to talk",
  "Mój mąz mówi trochę po polsku": "My husband speaks a little Polish",
  "Mój tata i mój brat mają trudny charakter": "My dad and my brother have difficult characters",
  "Mój tata nie gotowal dużo": "My dad didn't cook much",
  "Mówimy po hiszpańsku": "We speak Spanish",
  "Mówię po hiszpańsku": "I speak Spanish",
  "Młodzi nie mają pieniędzy": "Young people have no money",
  "NIe lubi ludzi , polityki": "He doesn't like people or politics",
  "NIe mam tatuaży": "I don't have any tattoos",
  "NIe rozmawialiśmy gdzie ona mieszka": "We didn't talk about where she lives",
  "NIe rozmawiam z matką Agaty przez telefon": "I don't talk to Agata's mother on the phone",
  "Na którym piętrze mieszkasz?": "Which floor do you live on?",
  "Napisałem do mojej przyjaciółki Ewy": "I wrote to my friend Ewa",
  "Nauczyciel w szkole zarabia małe pieniądze": "A school teacher earns little money",
  "Nie daje dużo pieniędzy": "It doesn't make a lot of money",
  "Nie dzwonię do Agaty": "I'm not calling Agata",
  "Nie lubimy podróżować samolotem": "We don't like traveling by plane",
  "Nie lubimy tego samego stylu muzyki": "We don't like the same style of music",
  "Nie lubię krótkich włosów u kota": "I don't like short hair on cats",
  "Nie lubię moich nóg": "I don't like my legs",
  "Nie lubię tego miasta": "I don't like this city",
  "Nie mam dużo pracy": "I don't have much work",
  "Nie mam zasięgu": "I don't have reception",
  "Nie masz problemów": "You have no problems",
  "Nie pada śnieg": "It's not snowing",
  "Nie piłem kawy od 10 lat": "I haven't had coffee in 10 years",
  "Nie pytali mnie": "They didn't ask me",
  "Nie robiłem nic specjalnego": "I didn't do anything special",
  "Nie taka duża jak mój dom": "Not as big as my house",
  "Nie wiem czy by mi się podobał": "I don't know if I would like it",
  "Nie wiem czy to jest dobre czy straszne": "I don't know if this is good or terrible",
  "Nie wiem gdzie są moje rękawiczki": "I don't know where my gloves are",
  "Nie wiem ile ma teraz": "I don't know how old he is now",
  "Nie wybieram się nigdzie": "I'm not going anywhere",
  "Nie znam dużo ludzi , którzy grają w golfa w moim wieku": "I don't know many people my age who play golf",
  "Nie znam nikogo": "I do not know anyone",
  "Nie znam wielu osób bez tatuaży": "I don't know many people without tattoos",
  "Niemcy": "Germany",
  "Nigdy nie chodzę do kawiarnii": "I never go to cafes",
  "Norwegia": "Norway",
  "Nowy Rok": "New year",
  "O naszej rodzinie": "About our family",
  "Od 3 lat": "From 3 years",
  "Oglądaliśmy wystawy": "We watched exhibitions",
  "On - go- jego- niego": "He- go- his- him",
  "On był bardzo niekulturalny": "He was very uncultured",
  "On był rasistą": "He was a racist",
  "On był uczonym": "He was a scholar",
  "On chce pomóc": "He wants to help",
  "On dużo podróżuje": "He travels a lot",
  "On golił się": "He was shaving",
  "On jadł": "He ate",
  "On jadł w pubie": "He ate in the pub",
  "On jest Węgrem": "He is Hungarian",
  "On jest dobry": "He is good",
  "On jest draniem": "He's a bastard",
  "On jest malarzem": "He is a painter",
  "On jest mechanikiem": "He is a mechanic",
  "On jest rozwiedziony": "He is divorced",
  "On jest studentem": "He is a student",
  "On jest z Torunia": "He is from Toruń",
  "On jest łysy": "He is bald",
  "On krzyczy": "He screams",
  "On lubi mówić o gotowaniu": "He likes to talk about cooking",
  "On ma 2 córki i jednego syna": "He has 2 daughters and one son",
  "On ma dużo klientów, ma swój warsztat": "He has a lot of clients, he has his own workshop",
  "On ma trzech pracowników": "He has three employees",
  "On maluje jako hobby": "He paints as a hobby",
  "On mial wizyte u dentysty": "He had a dentist appointment",
  "On musi pracować": "He has to work",
  "On nie jest dobry dla mojej przyjaciółki": "He's not good to my friend",
  "On nie jest rozmowmy": "He's not talkative",
  "On nie lubi kiedy my śpimy": "He doesn't like it when we sleep",
  "On poszedł": "He went",
  "On poszedł do pubu na urodziny Magdy": "He went to the pub for Magda's birthday",
  "On poszedł spać": "He went to sleep",
  "On pracuje jako mechanik od 30 lat.": "He has been working as a mechanic for 30 years.",
  "On pracuje w różnych miejsce": "He works in different place",
  "On projektuje na komputerze": "He designs on the computer",
  "On rozwiódł się": "He got divorced",
  "On spotkał się z Dominiką": "He met Dominika",
  "On źle pracuje": "He doesn't work well",
  "Ona 14 lat": "She is 14 years old",
  "Ona była dzieckiem": "She was a child",
  "Ona była na festiwalu": "She was at the festival",
  "Ona była tam przez 5 lat": "She was there for 5 years",
  "Ona chce być nauczycielką": "She wants to be a teacher",
  "Ona chce wejść do tramwaju": "She wants to get on the tram",
  "Ona chodzi do pracy pieszo": "She walks to work",
  "Ona chodzi zawsze do biura": "She always goes to the office",
  "Ona dzisiaj jedzie do biura busem": "She's going to the office by bus today",
  "Ona dzisiaj nie idzie na spacer": "She's not going for a walk today",
  "Ona dzisiaj piła kawę": "She drank coffee today",
  "Ona gotowala kurczaka": "She was cooking chicken",
  "Ona idzie do biura dzisiaj": "She's going to the office today",
  "Ona jest": "She is",
  "Ona jest Greczynką": "She is Greek",
  "Ona jest artystką": "She is an artist",
  "Ona jest dobrym muzykiem": "She is a good musician",
  "Ona jest fotografem": "She is a photographer",
  "Ona jest malarka": "She is a painter",
  "Ona jest milsza od siostry": "She is nicer than her sister",
  "Ona jest nauczycielką": "She is a teacher",
  "Ona jest pielęgniarką": "She is a nurse",
  "Ona jest piosenkarką": "She is a singer",
  "Ona jest piękna": "She is beautiful",
  "Ona jest programistką": "She is a programmer",
  "Ona jest rozwiedziona": "She is divorced",
  "Ona jest starsza": "She is older",
  "Ona jest starszą osobą": "She is an older person",
  "Ona jest strarszą panią": "She's an old lady",
  "Ona jest w moim wieku": "She is in my age",
  "Ona lubi być w domu": "She likes being at home",
  "Ona lubi czarny i niebieski": "She likes black and blue",
  "Ona lubi inną muzykę niż ja": "She likes different music than me",
  "Ona lubi pieniądze": "She likes money",
  "Ona lubi żartować": "She likes to joke",
  "Ona ma 15 lat.": "She is 15 years old.",
  "Ona ma covida": "She has covid",
  "Ona ma dużo problemów": "She has a lot of problems",
  "Ona ma duży dom": "She has a big house",
  "Ona ma dwadzieścia lat": "She is twenty years old",
  "Ona ma dwadzieścia trzy lata": "She is twenty-three years old",
  "Ona ma plany": "She has plans",
  "Ona ma trójkę dzieci": "She has three children",
  "Ona ma warsztat samochodowy": "She has a car repair shop",
  "Ona mieszka na zachodzie": "She lives in the west",
  "Ona mieszka na łodzi": "She lives on a boat",
  "Ona mieszka w Atenach": "She lives in Athens",
  "Ona mieszka w Lizbonie": "She lives in Lisbon",
  "Ona może sprzedawać swoją biżuterię": "She can sell her jewelry",
  "Ona musi rozmawiać z klientami": "She has to talk to customers",
  "Ona mówi szybko": "She speaks quickly",
  "Ona mówi za szybko": "She talks too fast",
  "Ona mówi że mężczyzna angielski jest przystojniejszy niż polski": "She says that an English man is more handsome than a Polish one",
  "Ona nie jest z mojego pokolenia": "She's not from my generation",
  "Ona nie lubi akcentu brytyjskiego w telewizji": "She doesn't like British accents on TV",
  "Ona nie lubi mówić po polsku": "She doesn't like speaking Polish",
  "Ona nie lubi rozmawiać z polakami": "She doesn't like talking to Poles",
  "Ona nie lubi społeczeństwa": "She doesn't like society",
  "Ona nie lubi spódnic": "She doesn't like skirts",
  "Ona nie nosi tego od 20 lat": "She hasn't worn it in 20 years",
  "Ona nie odbiera telefonu": "She doesn't answer the phone",
  "Ona nie pracuje na cały etat": "She doesn't work full time",
  "Ona nie pracuje w tej samej firmie": "She doesn't work in the same company",
  "Ona odebrała, ona nie miała zasięgu": "She answered, she had no reception",
  "Ona odwiedza nas": "She visits us",
  "Ona odwiedza nas co 2 lub 3 lata": "She visits us every 2 or 3 years",
  "Ona patrzy na lewo": "She looks to the left",
  "Ona pije kawę codziennie": "She drinks coffee every day",
  "Ona pisze interesujące piosenki": "She writes interesting songs",
  "Ona pomagała dziecku w lekcjach": "She helped the child with his homework",
  "Ona poszła": "She went",
  "Ona potrzebowała dziś mojej pomocy": "She needed my help today",
  "Ona powie mi o koncertach": "She will tell me about the concerts",
  "Ona przyjeżdża na weekend": "She's coming for the weekend",
  "Ona robi biżuterię": "She makes jewelry",
  "Ona rozwiodła się": "She got divorced",
  "Ona rozwiodła się w tym roku": "She got divorced this year",
  "Ona rzuca piłkę o ścianę": "She throws the ball against the wall",
  "Ona straciła akcent": "She lost her accent",
  "Ona uczyła się": "She was studying",
  "Ona urodziła się w Warszawie": "She was born in Warsaw",
  "Ona w pracy ma dużo polaków": "She has a lot of Poles at work",
  "Ona woli płaszcz": "She prefers a coat",
  "Ona wybrała pracę w banku": "She chose to work in a bank",
  "Ona zawsze jeździ do biura busem": "She always goes to the office by bus",
  "Ona zna więcej polskich miast od Agaty": "She knows more Polish cities than Agata",
  "One mają proste prace": "They have simple jobs",
  "One nudziły się": "They were bored",
  "One są żonami": "They are wives",
  "Oni bardzo lubią Budapeszt": "They like Budapest very much",
  "Oni grają na gitarze,": "They are playing the guitar,",
  "Oni jadą nad morze": "They're going to the seaside",
  "Oni lubią": "They like",
  "Oni mają działkę": "They have a plot of land",
  "Oni mają różne skarpetki": "They have different socks",
  "Oni mieszkają w małym mieście": "They live in a small town",
  "Oni nie lubią dużych miast": "They don't like big cities",
  "Oni nie lubią sportu": "They don't like sports",
  "Oni nie słuchają": "They don't listen",
  "Oni podróżują": "They travel",
  "Oni się huśtają": "They swing",
  "Oni się opalają": "They are sunbathing",
  "Oni sprzedali": "They sold",
  "Oni są nastolatkami": "They are teenagers",
  "Oni są starsi": "They are older",
  "Oni są starzy": "They are old",
  "Oni są trudni": "They are difficult",
  "Oni wolą": "They prefer",
  "Oni zbierają jabłka": "They are picking apples",
  "Ono jest dzieckiem": "It is a child",
  "Ono jest młode": "It's young",
  "Ostatni raz widzieliśmy się 5 lat temu": "The last time we saw each other was 5 years ago",
  "Park Łazienkowski": "Łazienkowski Park",
  "Pierwszy raz o 5 lat": "First time by 5 years",
  "Piszemy normalne wiadomości": "We write normal messages",
  "Pociąg jest z lotniska": "The train is from the airport",
  "Podobać się": "Please",
  "Pojechalismy autobusem": "We went by bus",
  "Polityka jest skomplikowana": "Politics is complicated",
  "Polska jest w trudnym momencie politycznym": "Poland is in a difficult political moment",
  "Portugalia": "Portugal",
  "Poszliśmy do restauracji": "We went to a restaurant",
  "Pracowałem dziś w domu u mojej przyjaciółki": "I was working at my friend's house today",
  "Pracujecie razem?": "Do you work together?",
  "Praga": "Prague",
  "Preply": "Preply",
  "Przyjaciółki Agaty to moje przyjaciółki": "Agata's friends are my friends",
  "Próbowałem": "I tried",
  "RTV i AGD": "Electronics and household appliances",
  "Rosja": "Russia",
  "Sent": "Sent",
  "Skąd jesteś": "Where are you from",
  "Skąd ona jest": "Where is she from",
  "Stany Zjednoczone": "United States",
  "Stany Zjednoczone- USA": "United States- USA",
  "Sylwester": "New Year's Eve",
  "Szkocja": "Scotland",
  "Szwajcaria": "Switzerland",
  "Szwecja": "Sweden",
  "Szwecja wygrała": "Sweden won",
  "TVP": "TVP",
  "Tak ja jadę": "Yes, I'm going",
  "Tak nie było za starych czasów": "It wasn't like that in the old days",
  "Tam": "Over there",
  "Tam nie ma nic ciekawego": "There's nothing interesting there",
  "This message was deleted": "This message was deleted",
  "To był pierwszy raz": "It was the first time",
  "To był prezent od mojej byłej": "It was a gift from my ex",
  "To była restauracja polska": "It was a Polish restaurant",
  "To było stresujący": "It was stressful",
  "To jest bardzo drogie": "It's very expensive",
  "To jest dobre kiedy pada deszcz": "It's good when it rains",
  "To jest jej obojętne": "She doesn't care",
  "To jest na połu": "It's halfway",
  "To jest na południowym zachodzie": "This is in the southwest",
  "To jest nowa działka": "This is a new plot",
  "To jest o niczym": "This is about nothing",
  "To jest rozrywka": "This is entertainment",
  "To jest sport dla ludzi którzy mają pieniądze": "This is a sport for people who have money",
  "To jest takie pokolenie": "This is that generation",
  "To jest trudne dla normalnych ludzi": "This is hard for normal people",
  "To możliwe": "It's possible",
  "To na samo co na ślub": "It's just for the wedding",
  "To nie jest interesujący dla mnie kraj": "This is not an interesting country for me",
  "To nie jest mój styl": "This is not my style",
  "To nie jest popularne miejsce": "This is not a popular place",
  "To nie jest problem dług": "This is not a debt problem",
  "To zajęło mi za dużo czasu": "This took me too long",
  "To łatwe dla bogatych ludzi": "It's easy for rich people",
  "Trrudno powiedzieć": "It's hard to say",
  "Trzymaj się": "Take care",
  "Tue, 13 Dec": "Tue, 13 Dec",
  "Tutaj": "Here",
  "Ty musisz studiować na uniwersytecie": "You have to study at university",
  "Ty nie chcesz nic robić": "You don't want to do anything",
  "Ty nie masz motywacji": "You have no motivation",
  "Tylko na ślub": "Only for the wedding",
  "Tym razem nie będzie dobrze": "This time it won't be good",
  "Ukraina": "Ukraine",
  "Urodziłem się": "I was born",
  "W Szkocii i Walii": "In Scotland and Wales",
  "W banku ona zarabia więcej pieniędzy": "She earns more money at the bank",
  "W czym mogę pani pomóc?": "How can I help you?",
  "W innym kraju robię inne rzeczy": "In another country I do different things",
  "W jakiej szkole pracujesz?": "What school do you work at?",
  "W jakim języku ona mów": "What language does she speak?",
  "W lipcu": "In July",
  "W pubie": "In pub",
  "W zeszłych latach": "In recent years",
  "Walia": "Wales",
  "Wczoraj byłem na starym mieście": "Yesterday I was in the old town",
  "Wielka Brytania": "Great Britain",
  "Wiem co robię": "I know what I'm doing",
  "Will be a few moments late, sorry...": "Will be a few moments late, sorry...",
  "Większość moich przyjaciół": "Most of my friends",
  "Wolę płaszcz niż kurtkę": "I prefer a coat over a jacket",
  "Wystawy w muzeum": "Exhibitions in the museum",
  "Węgry": "Hungary",
  "Włochy": "Italy",
  "Znam go": "I know him",
  "Znam ją ze szkoły": "I know her from school",
  "a": "and",
  "a moja siostra nie": "and my sister doesn't",
  "a teraz to jest duże miasto": "and now it's a big city",
  "ach": "ah",
  "aktualnie": "currently",
  "aktywne": "active",
  "ale ja muszę pracować": "but I have to work",
  "ale nie lubi gotować często": "but he doesn't like to cook often",
  "ale pracuje w banku": "but he works in a bank",
  "alkoholu": "alcohol",
  "ambitny": "ambitious",
  "amerykański angielski": "American English",
  "angielski jest łatwy": "English is easy",
  "animowane": "animated",
  "architekt projektuje budynki": "architect designs buildings",
  "artykuł": "article",
  "artykuły akademickie": "academic articles",
  "artysta": "artist",
  "austria": "Austria",
  "baletowe": "ballet",
  "bardziej": "more",
  "bardzo ładna pogoda": "very nice weather",
  "barszcz w proszku": "borscht powder",
  "basen": "swimming pool",
  "basenie - na basenie": "swimming pool - at the swimming pool",
  "bawić sie z psem": "play with the dog",
  "bawić się z kotami": "play with cats",
  "bawić się ze zwierzętami": "play with animals",
  "bać się - to be afraid": "to be afraid",
  "bezbożne": "unholy",
  "bezpośrednio": "directly",
  "biegać": "to run",
  "bierzesz lekarstwa": "you take medicine",
  "biorę": "I take it",
  "biurko - na biurku": "desk - on the desk",
  "biuro - w biurze": "office - in the office",
  "biżuteria": "jewelry",
  "blisko Walii": "close to Wales",
  "blisko jest drugi dom": "there is a second home nearby",
  "bliźniak - twin": "twin - twin",
  "bo mój akcent był trudny": "because my accent was difficult",
  "bogate osoby": "rich people",
  "boję się latać samolotem": "I'm afraid of flying",
  "boli mnie": "it hurts me",
  "botki": "ankle boots",
  "botki/ buty sportowe": "ankle boots/sports shoes",
  "bratanek , bratanica": "nephew, niece",
  "bratanica bratanek": "niece nephew",
  "bratanice, bratanka": "nieces, nephew",
  "brać": "to take",
  "brać - ja biorę prysznic": "take - I take a shower",
  "brać kredyt": "take a loan",
  "brytyjczykiem": "British",
  "bryza": "breeze",
  "budzić się": "wake up",
  "burza": "storm",
  "but- buty": "shoe- shoes",
  "buty zimowe": "winter boots",
  "bułka - bułki": "roll - rolls",
  "byli w Budapeszcie": "they were in Budapest",
  "byliśmy na plaży": "we were at the beach",
  "byliśmy na spacerze": "we went for a walk",
  "byliśmy w sklepie": "we were in the store",
  "być czesane": "be combed",
  "być na zakupach": "be shopping",
  "być w domu": "to be at home",
  "była 5 lat temu": "was 5 years ago",
  "była dobra": "she was good",
  "była dobra pogoda przez 2 dni": "the weather was good for 2 days",
  "była zmiana czasu": "there was a time change",
  "byłem na koncercie": "I was at the concert",
  "byłem z przyjaciółką i jej psem": "I was with a friend and her dog",
  "było ciepło": "It was warm",
  "było ciepło?": "It was warm?",
  "były": "were",
  "były koncerty": "there were concerts",
  "były partner": "former partner",
  "będziemy czytać i oglądać telewizję": "we will read and watch TV",
  "będziemy jeść kolację": "we will eat dinner",
  "będziemy w domu": "we will be home",
  "całe życie oglądam": "I've been watching all my life",
  "cały": "whole",
  "cały dzień": "whole day",
  "cały dzień mam spotkanie": "I have a meeting all day",
  "cały dzień tydzień": "all day a week",
  "cały etat": "full-time",
  "cały tydzień": "a whole week",
  "cały tydzień pracuję w domu": "I work from home all week",
  "centrum handlowe- w centrum handlowym": "shopping center - in a shopping center",
  "chce mi się pić": "I'm thirsty",
  "chce mówić z nią po polsku.": "I want to speak Polish with her.",
  "chcesz być pisarzem": "you want to be a writer",
  "chcą przyjechać za 2 dni": "they want to arrive in 2 days",
  "chcę jechać do Grecji, Słowenii": "I want to go to Greece, Slovenia",
  "chleb z kiełbasą": "bread with sausage",
  "chodzic na koncerty": "go to concerts",
  "chodzimy do teatru": "we go to the theater",
  "chodzić": "go",
  "chodzić - on chodził w góry": "walk - he went to the mountains",
  "chodzić pieszo -": "walk -",
  "chodzić po góra": "walk up the mountain",
  "chodzę do pracy codziennie": "I go to work every day",
  "chodzę schodami": "I take the stairs",
  "chodzę schodami kiedy winda jest zepsuta": "I take the stairs when the elevator is broken",
  "chodzę spacerem": "I walk",
  "choinka": "Christmas tree",
  "chora": "sick",
  "chory": "sick",
  "chudy": "skinny",
  "chętnie": "gladly",
  "ciasta i ciastka": "cakes and cookies",
  "ciastko": "cookie",
  "ciasto": "cake",
  "ciasto - ciastko": "cake - cookie",
  "ciemno": "dark",
  "ciepło": "warm",
  "ciocia": "Aunt",
  "ciąć": "cut",
  "co 6 miesięcy": "Every 6 months",
  "co drugi rok": "every other year",
  "co dwa tygodnie oglądamy stare Eurowizje": "we watch old Eurovision songs every two weeks",
  "co pół roku": "every six months",
  "co roku": "every year",
  "co się stało?": "What happened?",
  "co wolisz?": "what do you prefer?",
  "codziennie": "every day",
  "confirm the lesson please": "confirm the lesson please",
  "contract - umowa": "contract - contract",
  "coś jeszcze?": "something else?",
  "cukiernia - w cukiernii": "confectionery shop - in the confectionery shop",
  "czapka z daszkiem": "cap",
  "czarne oczy": "black eyes",
  "czarny płaszcz": "a black coat",
  "czarny skórzany płaszcz": "black leather coat",
  "czas zawodowy": "professional time",
  "czasami": "Sometimes",
  "czasami jeżdżę pociągiem": "sometimes I travel by train",
  "czasami kolega pożycza mi książki": "sometimes a friend lends me books",
  "czasami pożyczam od kolegi": "sometimes I borrow from a friend",
  "czasami tak robię": "sometimes I do that",
  "czekam na Panią / pana": "I'm waiting for you ma'am/sir",
  "czekać": "wait",
  "czerwiec - lipiec": "June July",
  "czesać koty": "comb the cats",
  "cześć": "Hi",
  "czterdzieści": "forty",
  "czterdzieści jeden": "forty one",
  "czy dla pieniędzy": "or for money",
  "czy tam mieszka twoja rodzina?": "does your family live there?",
  "czy ty chodzisz późno spać?": "do you go to bed late?",
  "czy ty letem pływasz w morzu?": "do you swim in the sea in the summer?",
  "czy wolisz dzwonić czy wysyłać wiadomości?": "Do you prefer calling or sending messages?",
  "czy wy znacie się długo": "have you known each other for a long time?",
  "czytam": "I am reading",
  "czytam książkę": "I read a book",
  "czytać": "to read",
  "czytałem": "I read",
  "często": "often",
  "często tam gram": "I play there often",
  "część gitary": "part of the guitar",
  "część samolotu uderzyła mnie w plecy": "part of the plane hit my back",
  "dentka": "dentist",
  "dla czasopisma": "for the magazine",
  "dla dorosłych": "for adults",
  "dla mnie": "for me",
  "dla mnie nie jest gorąco": "It's not hot for me",
  "dla muzyków i poetów": "for musicians and poets",
  "dla młodych ludzi": "for young people",
  "dla nas": "for us",
  "dla obcokrajowców": "For foreigner",
  "dla przyjaciela": "for a friend",
  "dla rodziny": "for family",
  "dla swojej sztuki": "for your art",
  "dla uniwersytetu": "for the university",
  "dla wszystkich": "for everyone",
  "dlatego idziemy do zoo": "that's why we're going to the zoo",
  "dlatgo jest gorąco": "that's why it's hot",
  "dna moczanowa": "gout",
  "dniowym- zachodzie Anglii": "day-west of England",
  "do domu": "to home",
  "do dziewiątej": "until nine",
  "do fryzjera": "to hairdresser",
  "do góry": "up",
  "do którego lekarza?": "which doctor?",
  "do lasu": "to the forest",
  "do moich rodziców": "to my parents",
  "do moich rodziców?": "to my parents?",
  "do rodziny": "to the family",
  "do wynajęcia": "for rent",
  "dobra pogoda na trzy dni": "good weather for three days",
  "dobrym pisarzem": "a good writer",
  "dobrze": "All right",
  "dobrze - lepiej - najlepiej": "good better the best",
  "dobrze poszło": "it went well",
  "domek": "cottage",
  "dostaję oferty": "I get offers",
  "dostarczyć": "deliver",
  "dostać w prezencie": "get as a gift",
  "dostępny": "available",
  "drabina": "ladder",
  "drań": "bastard",
  "drogeria - w drogerii": "drugstore - in the drugstore",
  "drogeria natura": "nature drugstore",
  "drogerii": "drugstore",
  "drogi": "Dear",
  "druga córka": "second daughter",
  "druga przyjaciółka": "second friend",
  "drzewa": "trees",
  "drzewo": "tree",
  "dużo warzyw": "a lot of vegetables",
  "dużo zaproszeń": "lots of invitations",
  "dwadzieścia lat": "twenty years",
  "dwadzieścia lat temu": "twenty years ago",
  "dwadzieścia minut": "twenty minutes",
  "dwadzieścia osiem": "twenty eight",
  "dwie córka": "two daughter",
  "dwieście stron": "two hundred pages",
  "dworzec": "station",
  "dwulicowy": "two-faced",
  "działka": "plot",
  "dziecko": "kid",
  "dziecko - dzieckiem": "child - child",
  "dziesięc lat w Hiszpanii": "ten years in Spain",
  "dziesięć osób": "ten people",
  "dzień wolny": "day off",
  "dzisiaj": "Today",
  "dzisiaj był pierwszy dzień pracy": "today was the first day of work",
  "dzisiaj jest święto": "it's a holiday today",
  "dzisiaj mamy wolne": "we have today off",
  "dzisiaj nie ide pracy": "I'm not going to work today",
  "dzisiaj padał deszcz": "it was raining today",
  "dzisiaj wieczorem": "tonight",
  "dzwonić": "call",
  "dług": "debt",
  "dżem": "jam",
  "east": "east",
  "efekty pocovidowe": "post-covid effects",
  "ekran": "screen",
  "eksperymentalna": "experimental",
  "elastyczny czas pracy": "flexible working time",
  "eleganckie spodnie": "elegant trousers",
  "em, ą - ami": "em, ą - ami",
  "fajerweki": "fireworks",
  "fasola": "beans",
  "filmy są amerykańskie": "the movies are american",
  "filozofię": "philosophy",
  "fotografować": "photograph",
  "garaż - w garażu": "garage - in the garage",
  "gardło": "throat",
  "garnitur": "suit",
  "garniturów": "suits",
  "gazeta- gazety": "newspaper - newspapers",
  "gazeta- w gazecie": "newspaper - in the newspaper",
  "gdzie": "Where",
  "gdzie gracie?": "where are you playing?",
  "golić się": "shave",
  "gorąco": "hot",
  "gospodarstwo agroturystyczne": "agritourism farm",
  "gospodarz": "host",
  "gospodyni": "hostess",
  "gotowaliśmy": "we cooked",
  "gotować": "to cook",
  "gotowałem za długo": "I cooked too long",
  "gotujemy": "we cook",
  "grafikiem komputerowym": "computer graphic designer",
  "gram dużo na gitarze": "I play a lot of guitar",
  "gram z moimi kolegami": "I play with my friends",
  "gram z moimi przyjaciółmi": "I play with my friends",
  "gramy w gry internetowe": "we play online games",
  "granatowa": "Navy",
  "granica": "border",
  "grać w piłkę, w koszykówkę,, siatkówkę": "play football, basketball, volleyball",
  "grałem na instrumencie": "I played an instrument",
  "grałem trochę": "I played a little",
  "grałem w domu": "I played at home",
  "grube": "thick",
  "gruby": "fat",
  "góra": "Mountain",
  "gęś": "goose",
  "hasło": "password",
  "hałas": "noise",
  "hipsterskie": "hipster",
  "https://www.polskinawynos.com/bank-slowek/": "https://www.polskinawynos.com/bank-slowek/",
  "huśtawka": "swing",
  "i": "and",
  "i groszek": "and peas",
  "i internet": "and internet",
  "i owoców": "and fruit",
  "i potem muszę czekać godzinę": "and then I have to wait an hour",
  "i rozmawiamy": "and we talk",
  "i sztuka": "and art",
  "i teraz ona ma problemy ze zdrowiem": "and now she has health problems",
  "i trudno": "and it's hard",
  "i z psem": "and with a dog",
  "idziemy do zoo": "we're going to the zoo",
  "idę do łazienki": "I'm going to the bathroom",
  "idę spać": "I'm going to bed",
  "ile godzin?": "how many hours?",
  "indyk": "turkey",
  "informatyką": "information technology",
  "instrument": "instrument",
  "inteligentny": "intelligent",
  "intensywnie pracuję": "I work hard",
  "interesować się": "interest in",
  "interesujący kształt": "interesting shape",
  "iśc do weterynarza": "go to the vet",
  "iść": "to go",
  "iść , chodzić": "go, walk",
  "iść - poszedłem": "go - I went",
  "iść - to walk": "to go - to walk",
  "iść do pracy": "go to work",
  "iść do łazienki": "go to the bathroom",
  "iść na imprezę z przyjaciółmi": "go to a party with friends",
  "iść na plażę": "go to the beach",
  "iść na uniwersytet": "go to university",
  "iść nad rzekę": "go to the river",
  "iść spać-": "go to sleep-",
  "ja - mnie": "I - me",
  "ja biorę kredyt": "I take a loan",
  "ja boję się": "I'm afraid",
  "ja byłem na spacerze": "I was on a walk",
  "ja byłem, byłam": "I was, I was",
  "ja byłem, ja byłam": "I was, I was",
  "ja chcę pojechać do Budapesztu": "I want to go to Budapest",
  "ja czekam": "I'm waiting",
  "ja gotuję": "I cook",
  "ja gram na skrzypcach i gitarze": "I play the violin and guitar",
  "ja gram sam": "I play alone",
  "ja idę": "I'm going",
  "ja idę dzisiaj na spacer": "I'm going for a walk today",
  "ja jadę": "I'm driving",
  "ja jadę - ja jechałem - ja pojechałem do sklepu": "I'm going - I was going - I went to the store",
  "ja jadłem obiad o 13": "I had dinner at 1 p.m",
  "ja jem - ja jadłem": "I eat - I ate",
  "ja jestem leniwy": "I'm lazy",
  "ja jeżdżę": "I am driving",
  "ja kupiłem zmywarkę": "I bought a dishwasher",
  "ja kupuję bizuterię w sklepie jubilerskim": "I buy jewelry in a jewelry store",
  "ja maluję": "I paint",
  "ja martwię się": "I am worried",
  "ja marzę o wakacjach": "I dream about holidays",
  "ja mieszkam na trzecim piętrze": "I live on the third floor",
  "ja myślałem o książce": "I was thinking about the book",
  "ja myślę , że oni nas lubią": "I think they like us",
  "ja nie jeżdżę konno": "I don't ride horses",
  "ja nie lubię garnituróe": "I don't like suits",
  "ja nie piję alkoholu": "I do not drink alcohol",
  "ja nie pracowałem dużo": "I didn't work much",
  "ja piję": "I drink",
  "ja piję herbatę lub sok": "I drink tea or juice",
  "ja piszę - ja pisałem": "I write - I wrote",
  "ja potrafię grać": "I can play",
  "ja powiedziałem , że": "I said that",
  "ja radzę sobie": "I'm coping",
  "ja robię": "I do",
  "ja skończyłem": "I finished",
  "ja wcale nie lubię": "I don't like it at all",
  "ja widzę pogodę za oknem": "I see the weather outside the window",
  "ja wolę": "I prefer",
  "ja wolę być w domu kiedy pada śnieg": "I prefer to be at home when it snows",
  "ja wstaję - I get up": "I get up - I get up",
  "ja wstaję o... ósmej": "I get up at... eight",
  "ja zawsze słucham muzyki,": "I always listen to music",
  "ja śpię": "IM sleeping",
  "ja śpię - ja spałem": "I'm sleeping - I was sleeping",
  "jadę do biura na rowerze": "I'm riding my bike to the office",
  "jak częste macie koncert?": "how often do you have concerts?",
  "jak poszło?": "how did it go?",
  "jakieś pytania": "any questions",
  "jako nauczyciel?": "as a teacher?",
  "jako programista": "as a programmer",
  "jarzynowa": "vegetable",
  "jechalismy 4 godziny": "we drove for 4 hours",
  "jechać": "to go",
  "jechać , jeździć": "go, ride",
  "jechać jeździć": "go ride",
  "jechać w góry - Oni jadą w góry": "go to the mountains - They are going to the mountains",
  "jedliście kolacje": "you had dinner",
  "jedliśmy": "we ate",
  "jedna para": "one pair",
  "jedno długie zdanie": "one long sentence",
  "jedynak": "only child",
  "jedzenie": "food",
  "jedziemy do": "we are going to",
  "jedziemy do domu": "we're going home",
  "jedziemy pociagiem i taksówką": "we go by train and taxi",
  "jej praca w USA się skończyła": "her job in the US is over",
  "jej starsza córka": "her older daughter",
  "jemy chleb , kanapki": "we eat bread and sandwiches",
  "jemy z": "we eat with",
  "jemy z rodzicami": "we eat with our parents",
  "jesienią pada deszcz": "it rains in autumn",
  "jesień": "autumn",
  "jest 7 po siódmej": "it's 7 past seven",
  "jest luty": "it's february",
  "jest najtrudniej zrozumieć": "is the hardest to understand",
  "jest naprawiona": "is fixed",
  "jest podobnie": "It is similarly",
  "jest siódma siedem": "it's seven seven",
  "jest z ?,": "is from ?,",
  "jest za dużo ludzi": "there are too many people",
  "jest zima": "it's winter",
  "jest ładnie": "its nice",
  "jest źle": "it's bad",
  "jestem na plaży": "I'm on the beach",
  "jestem programistą": "I am a programmer",
  "jestem roztopiony": "I'm melted",
  "jestem samoukiem": "I am self-taught",
  "jestem trochę chory": "I'm a little sick",
  "jesteśmy dorośli": "we are adults",
  "jesteśmy na urlop": "we are on vacation",
  "jeszcze": "still",
  "jeszcze nie mam": "I do not have it yet",
  "jezioro- w jeziorze": "lake - in the lake",
  "jeść": "eat",
  "jeść zdrowo": "eat healthy",
  "jeździc na nartach": "skiing",
  "jeździć": "ride",
  "jeździć na nartach": "skiing",
  "jeździć na rowerze": "ride a bicycle",
  "jeździć rowerem do biura": "ride a bike to the office",
  "jeździć samochodem": "drive a car",
  "jeżdżę na rowerze": "I ride a bike",
  "jeżdżę rowerem": "I ride a bike",
  "jeżdżę samochodem": "I drive a car",
  "jeżdżę windą na moje piętro": "I take the elevator to my floor",
  "jubiler - u jubilera": "jeweler - at the jeweler's",
  "kaczka ze szpinakiem": "duck with spinach",
  "karma dla kota": "cat food",
  "karmić": "feed",
  "karuzela jest w wesołym miasteczku": "The carousel is in the amusement park",
  "katastrofa": "catastrophe",
  "kawaler nie ma partnerki": "a bachelor has no partner",
  "kawaler/ panna": "bachelor/single",
  "kawiarnia": "coffeehouse",
  "kawiarnia - w kawiarnii": "cafe - in a cafe",
  "kiedy byliśmy w Warszawie": "when we were in Warsaw",
  "kiedy byłem dzieckiem": "when I was a child",
  "kiedy czytam": "when I read",
  "kiedy mam przerwę": "when I have a break",
  "kiedy mam za długie włosy noszę czapkę": "when my hair is too long I wear a hat",
  "kiedy piję kawę nie mogę spać": "when I drink coffee I can't sleep",
  "kiedy rozmawialiśmy ostatnim razem": "when we last talked",
  "kierowca": "driver",
  "kilka": "several",
  "kilometrów": "kilometers",
  "kim? czym?": "Who is? what?",
  "kino - w kinie": "cinema - at the cinema",
  "klapki": "flip-flops",
  "klimatyzacja": "air conditioning",
  "kobieta": "woman",
  "kobietą": "woman",
  "kocerty w parku": "concerts in the park",
  "kocioł": "cauldron",
  "kofeina": "caffeine",
  "kolacja": "Dinner",
  "kolacja-": "Dinner-",
  "koledzy": "friends",
  "kolega": "friend",
  "kolegami": "colleagues",
  "kolej Agatki": "Agatka's turn",
  "koleżanka": "girlfriend",
  "komunikatywna": "communicative",
  "koncert na działce": "concert on the plot",
  "konie": "horses",
  "korekta": "adjustment",
  "koronacja króla": "king's coronation",
  "kosmetyk - kosmetyki": "cosmetic - cosmetics",
  "koszula": "Shirt",
  "koszule i spodnie": "shirts and trousers",
  "koszulka": "shirt",
  "koszulka - koszula": "T-shirt - shirt",
  "kot jest chory": "the cat is sick",
  "koty rasowe": "purebred cats",
  "kościół": "church",
  "kościół - w kościele": "church - in the church",
  "krawat": "tie",
  "krowy": "cows",
  "krzesło - na krześle": "chair - on a chair",
  "krzyczeć": "scream",
  "krótko padał deszcz": "it rained briefly",
  "kręcone": "curly",
  "książka muzyczna": "music book",
  "książka na papierze": "book on paper",
  "książkami informatycznymi": "IT books",
  "książki o komupterach": "books about computers",
  "księgarnia": "bookstore",
  "która": "which",
  "którzy lubią kolorowe ubrania": "who like colorful clothes",
  "kuchenka na gaz": "gas stove",
  "kupić w sklepie": "buy in store",
  "kupiłam telewizor": "I bought a TV",
  "kupiłem tą książkę": "I bought this book",
  "kupuję- robię zakupy": "I buy - I shop",
  "kwiat - kwiaty": "flower - flowers",
  "kwiaty - flowers": "flowers - flowers",
  "kłócić się": "to argue",
  "kłócić się - oni kłócą się": "argue - they argue",
  "kłótliwy - kłócić się": "quarrelsome - to quarrel",
  "las": "forest",
  "las - forest": "forest",
  "lato": "summer",
  "lecimy samolotem do Polski": "we are flying to Poland",
  "leki - lekarstwa": "medicines - medicines",
  "leniwe": "lazy",
  "leniwy": "lazy",
  "lepiej": "Better",
  "leżeć na sofie": "lie on the sofa",
  "leżeć w łóżku": "stay in bed",
  "liceum": "high school",
  "linie lotnicze": "Airlines",
  "listy": "letters",
  "listę": "list",
  "lotnisko": "airport",
  "lubiałem narkotyki": "I liked drugs",
  "lubie bo nie pracuję": "I like it because I don't work",
  "lubimy śmiać się z naszych znajomych, rodziny.. etc.": "we like to laugh at our friends, family... etc.",
  "lubią bardziej sztukę niż sport": "they like art more than sports",
  "ludzi": "people",
  "ludzie mają włosy": "people have hair",
  "ludzie nie mogli mnie zrozumieć": "people couldn't understand me",
  "ludzie są mili": "people are nice",
  "ludzie, którzy oglądali": "people who watched",
  "ma dużo trudnych słów": "has a lot of difficult words",
  "ma koncert": "has a concert",
  "ma przebitą dentkę": "he has a punctured tooth",
  "makaron": "pasta",
  "makowiec": "poppy seed cake",
  "malować": "paint",
  "malować się": "to do a make up",
  "mam": "I have",
  "mam nowę gitarę": "I have a new guitar",
  "mam przyjaciół": "I have friends",
  "mam przyjaciółkę": "I have a friend",
  "mama Agaty jedzie do Warszawy zobaczyć nas": "Agata's mother is going to Warsaw to see us",
  "mama ją przywiozła": "Mom brought her",
  "marmolada": "marmalade",
  "martwić się": "worry",
  "marzenie - dream": "dream - dream",
  "marzę o tym": "I dream about it",
  "matka Agatki": "Agatka's mother",
  "mała wioska": "a little village",
  "małomówny": "taciturn",
  "meczet - w meczecie": "mosque - in the mosque",
  "meżczyzną": "man",
  "miasteczko": "town",
  "miasto": "city",
  "miasto - w mieście": "city - in the city",
  "miasto nad morzem": "city by the sea",
  "miasto rodzinne": "home town",
  "miałem szczęście": "I was lucky",
  "miejsce": "place",
  "mieliśmy duże szczęście": "we were very lucky",
  "mieliśmy ładną pogodę": "we had nice weather",
  "miesiąc": "month",
  "mieszać - to mix": "mix - it's a mix",
  "mieszka w": "lives in",
  "mieszkaniec-": "inhabitant-",
  "mieszkałem": "I lived",
  "mieć na imię / nazwisko": "have a name/surname",
  "miszkałem": "I mixed",
  "mięśnie": "muscles",
  "miły": "nice",
  "mlekiem": "milk",
  "mleko migdałowe": "Almond milk",
  "mleko owsiane": "oat milk",
  "mleko roślinne": "plant milk",
  "mleko sojowe": "soy milk",
  "mogę panu pomóc?": "can I help you?",
  "moi koledzy są irytujący": "my colleagues are annoying",
  "moi przyjaciele": "my friends",
  "moi przyjaciele mieszkają w....": "my friends live in....",
  "moi szefowie są na wakacjach": "my bosses are on vacation",
  "moja była": "my ex",
  "moja była partnerka": "my ex-partner",
  "moja matka jest z Irlandii": "my mother is from Ireland",
  "moja organizacja": "my organization",
  "moja praca jest intensywna": "my job is intense",
  "moja przyjaciółka": "my friend",
  "moja rodzina": "my family",
  "moja rodzina nie lubiła muzyki": "my family didn't like music",
  "moje koty się boją": "my cats are scared",
  "moje partnerki nie były angielkami": "my partners were not English",
  "morze- w morzu": "sea- in the sea",
  "most": "bridge",
  "może to kac": "maybe it's a hangover",
  "możemy iść pieszo do centrum,": "we can walk to the center,",
  "musiałem używać pralni": "I had to use the laundry room",
  "musieliśmy czekać": "we had to wait",
  "musisz iść": "you have to go",
  "musli": "muesli",
  "muzeach": "museums",
  "muzyka klasyczna": "Classical music",
  "muzykalny": "musical",
  "muzykiem": "musician",
  "muzyką klasyczną": "Classical music",
  "my boimy się": "we are afraid",
  "my dużo jedliśmy": "we ate a lot",
  "my idziemy razem do restauracji": "we go to the restaurant together",
  "my jeździmy do Włoch": "we go to Italy",
  "my odpoczywamy": "We are resting",
  "my rozmawialiśmy z rodzicami": "we talked to the parents",
  "my też nie": "neither do we",
  "my wolimy": "We prefer",
  "my zajmujemy się finansami": "we deal with finances",
  "my śpimy": "we are sleeping",
  "myję zęby": "I brush my teeth",
  "myzykę folkową / ludową": "folk / folk music",
  "myć się - ja myję się": "wash - I wash",
  "myć zęby": "brush your teeth",
  "myśleć o książce": "think about the book",
  "myślę, że tak": "I think so",
  "mój naturalny akcent": "my natural accent",
  "mój przyjaciel nas zawiózł do...": "my friend took us to...",
  "mówić": "to talk",
  "mąka": "flour",
  "mężatka": "married",
  "mężczyna": "man",
  "młode": "young",
  "młodsza": "younger",
  "młodszy - najmłodszy": "younger - the youngest",
  "na Boże Narodzenie": "for Christmas",
  "na basenie": "at the pool",
  "na długi weekend": "for a long weekend",
  "na górze": "at the top",
  "na imprezie": "at a party",
  "na instrumentach": "on instruments",
  "na jedenastym piętrze": "on the eleventh floor",
  "na kindlu": "on kindle",
  "na koncercie": "at the concert",
  "na lotnisku": "at the airport",
  "na pianinie": "on the piano",
  "na plaży , po plaży": "on the beach, after the beach",
  "na południowym zachodzie": "on the south-west",
  "na północy Anglii": "in the north of England",
  "na rowerze": "by bicycle",
  "na rzece": "on the river",
  "na spektakle": "for performances",
  "na sportowo": "for sports",
  "na starym mieście": "In the old town",
  "na stole": "on the table",
  "na urlopie": "on leave",
  "na wsi": "in the countryside",
  "na wybrzeże": "to the coast",
  "na wynos": "to go",
  "na zachodzie": "in the West",
  "na zewnątrz": "outside",
  "na ślub": "for wedding",
  "nad jeziorem": "by the lake",
  "nad morzem": "at the seaside",
  "nad rzeką": "by the river",
  "nadmuchany": "inflated",
  "najmłodszy": "the youngest",
  "najstrasze koty": "the scariest cats",
  "napompowany": "inflated",
  "naprawiać": "repair",
  "naprawiałem gitarę": "I was repairing a guitar",
  "naprawiałem moją gitarę": "I was repairing my guitar",
  "naprawić": "to fix",
  "narzekać": "to complain",
  "narzędzie": "tool",
  "naszymi znajomymi": "our friends",
  "naturę": "nature",
  "nauczycielką": "teacher",
  "naukowe": "scientific",
  "nazywać się": "to be called",
  "nazywać się , myć się": "call yourself, wash yourself",
  "nerwowy": "nervous",
  "nic": "nothing",
  "nic ciekawego": "nothing interesting",
  "nic nie robimy": "we are doing nothing",
  "nic nowego": "nothing new",
  "nic specjalnego": "nothing special",
  "nie brac narkotyków": "don't take drugs",
  "nie byliśmy w zoo": "We weren't at the zoo",
  "nie byłem poza domem": "I wasn't out",
  "nie chodzimy na imprezy": "we don't go to parties",
  "nie cierpi": "doesn't suffer",
  "nie czytasz": "you don't read",
  "nie dużo": "not much",
  "nie działa": "doesn't work",
  "nie jest drogi": "it's not expensive",
  "nie jest tak gorąco": "it's not that hot",
  "nie jestem zestresowany": "I'm not stressed",
  "nie jeżdżę": "I don't drive",
  "nie jeżdżę taksówką": "I don't take a taxi",
  "nie lubimy samolotów": "we don't like planes",
  "nie lubię fajerweków": "I don't like fireworks",
  "nie lubię oglądać filmów": "I don't like watching movies",
  "nie lubię spędzać czasu przed komputerem": "I don't like spending time in front of the computer",
  "nie lubię słodyczy": "I don't like sweets",
  "nie lubię tej książki": "I don't like this book",
  "nie ma": "There isn't",
  "nie ma klimatyzacja": "there is no air conditioning",
  "nie ma klimatyzacji": "there is no air conditioning",
  "nie ma sklepów": "there are no shops",
  "nie mamy zupy": "we don't have soup",
  "nie martw się": "Don't worry",
  "nie miałem": "I did not have",
  "nie mieliśmy gości": "we had no guests",
  "nie mogliśmy odmówić": "we couldn't say no",
  "nie mogę jeść sera": "I can't eat cheese",
  "nie mogę myśleć": "I can not think",
  "nie mogę żyć": "I can not live",
  "nie mogłem": "I could not",
  "nie mogłem dobrze spać": "I couldn't sleep well",
  "nie możemy": "we can not",
  "nie palić": "No smoking",
  "nie piję kawy": "I do not drink coffee",
  "nie pić": "don't drink",
  "nie pracujemy w tym samym miejscu": "we don't work in the same place",
  "nie robimy tego często": "we don't do this often",
  "nie sapceruję dzisiaj": "I'm not sapping today",
  "nie stresować się": "don't stress",
  "nie stresuję się": "I am not stressed",
  "nie słyszałem": "I have not heard",
  "nie w naszym domu": "not in our house",
  "nie widzieliśmy jej przez 2 lata": "We haven't seen her for 2 years",
  "nie wiedziałem czy pociąg pojedzie": "I didn't know if the train would go",
  "nie wiem jakie ona ma stanowisko": "I don't know what her position is",
  "nie wszyscy": "not everyone",
  "nie wszyscy kochają Eurowizję": "not everyone loves Eurovision",
  "nie wychodziłem z domu": "I didn't leave the house",
  "nie zapraszamy kolegów": "We don't invite friends",
  "nie zarabiałem dużo": "I didn't earn much",
  "niedobry": "bad",
  "niemili": "rude",
  "niepunktualny": "unpunctual",
  "nieśmiały": "shy",
  "niska": "short",
  "niski": "short",
  "no - tak": "Yeah",
  "nosić": "to wear",
  "noworoczne postanowienia": "New Year's resolutions",
  "np. trenować karate": "e.g. practice karate",
  "nudne": "boring",
  "nudne rozmowy": "boring conversations",
  "nóż": "knife",
  "o": "about",
  "o Fridzie Kahlo": "about Frida Kahlo",
  "o historii i polityce": "about history and politics",
  "o kotach": "about cats",
  "o której godzinie wstajesz?": "what time do you get up?",
  "o moderstwie": "about murder",
  "o narkotykach": "about drugs",
  "o prawie": "about law",
  "o programowaniu i komputerach": "about programming and computers",
  "o przyjaciołach": "about friends",
  "o północy": "midnight",
  "o siedemnastej- o piątej": "at seven-five",
  "o sporcie": "about sports",
  "o ósmej": "at eight",
  "obcokrajowcami": "foreigners",
  "obcokrajowcy": "foreigners",
  "obiad": "Lunch",
  "obowiązek": "duty",
  "obrazek": "picture",
  "obuwie - buty": "footwear - shoes",
  "obyczaje": "manners",
  "ocean - w oceanie": "ocean - in the ocean",
  "oczytany": "well-read",
  "od dziewiątej do piątej": "from nine to five",
  "od dziewiątej do siedemnastej": "from nine to seven",
  "od poniedziałku do piatku nie wychodzisz z domu?": "You don't leave home from Monday to Friday?",
  "od siódmego do czternastego lipca": "from July seven to fourteen",
  "odkurzacz": "vacuum cleaner",
  "odkurzać": "to vacuum",
  "odpisywać na maile": "reply to emails",
  "odpoczywamy": "we are resting",
  "odpoczywać": "relax",
  "odwiedza": "visits",
  "odwiedzają koty": "cats visit",
  "odwiedzałam rodzinę": "I was visiting family",
  "odwiedziliśmy rodzinę wcześniej": "we visited family earlier",
  "odwiedzić": "visit",
  "odwiedziła": "visited",
  "odwiedzć": "visit",
  "odwołać": "cancel",
  "odzież - ubrania - sklep odzieżowy": "clothing - clothes - clothing store",
  "oglądam telewizję": "I watch TV",
  "oglądać": "to watch",
  "oglądałem filmy": "I watched movies",
  "około 6 kilometrów": "about 6 kilometers",
  "okulary przeciwsłoneczne": "Sunglasses",
  "on": "he",
  "on boi się": "he is scared",
  "on chciał uczyc mnie węgierskiego": "he wanted to teach me Hungarian",
  "on idzie": "He goes",
  "on jest artystą": "he is an artist",
  "on jest kierowcą": "he is the driver",
  "on jest zabawny": "he is funny",
  "on jest zepsuty": "he is broken",
  "on jest zły": "he is angry",
  "on jest żonata": "he is married",
  "on jest żonaty": "he is married",
  "on maluje postacie z gier komputerowych": "he paints computer game characters",
  "on miał mikrofon z TVP": "he had a microphone from TVP",
  "on poszedł do dentysty": "he went to the dentist",
  "on robił zdjęcia": "he was taking photos",
  "on spacerował w górach": "he was walking in the mountains",
  "on tańczy profesjonalnie": "he dances professionally",
  "on umarł- he died": "he died- he died",
  "on woli": "He prefers",
  "on wstał": "he woke up",
  "on śpi": "he sleeps",
  "ona bierze leki / lekarstwa": "she takes medication/medication",
  "ona była chora": "she was sick",
  "ona była z nami": "she was with us",
  "ona była zajęta": "she was busy",
  "ona chce żebyśmy dużo jeździli do Polski": "she wants us to go to Poland a lot",
  "ona jest aktywistką polityczną": "she is a political activist",
  "ona jest małomówna": "she is taciturn",
  "ona jest mężatką": "She is married",
  "ona jest sprzedawczynią": "she is a saleswoman",
  "ona jest urzędniczką z zawodu": "she is a clerk by profession",
  "ona jest zadowolona": "she is glad",
  "ona lubi książki": "she likes books",
  "ona ma wiele imion": "she has many names",
  "ona ma wózek inwalidzki": "she has a wheelchair",
  "ona miała wylew": "she had a stroke",
  "ona myła podłogę": "she was washing the floor",
  "ona mówi że my nie podróżujemy": "she says we don't travel",
  "ona nie ma rowera": "she doesn't have a bike",
  "ona nie odpowiada na maile": "she doesn't respond to emails",
  "ona nie rozmiawa dużo z ludźmi": "she doesn't talk to people much",
  "ona oglądała": "she was watching",
  "ona poszla spać": "she went to sleep",
  "ona pracuje": "she works",
  "ona przyjechała samochodem": "she came by car",
  "ona robi barszcz czerwony": "she makes red borscht",
  "ona umarła": "she died",
  "ona upiekła ciasto": "she baked a cake",
  "ona wróciła do Anglii": "she returned to England",
  "ona zamawiała": "she ordered",
  "ona zaprosiła nas do swojego domu": "she invited us to her house",
  "one są głośne": "they are loud",
  "one są spokojne": "they are calm",
  "oni boją się": "they're scared",
  "oni dyskutują": "they are discussing",
  "oni lubi motyle": "they like butterflies",
  "oni muszą przynieść deser": "they have to bring dessert",
  "oni mówili szybko": "they spoke quickly",
  "oni nas zaprosili do ich domu": "they invited us to their house",
  "oni nie są dobrymi kucharzami": "they are not good cooks",
  "oni powiedzieli": "they said",
  "oni płacą dużo": "they pay a lot",
  "oni są wegetarianami": "they are vegetarians",
  "oni wolą": "they prefer",
  "oni z kraju Basków": "they are from the Basque country",
  "oni śpią": "they are sleeping",
  "opalać sie": "to sunbathe",
  "oprócz": "apart from",
  "opóźnienie": "delay",
  "orzeszki": "Peanuts",
  "osiemdziesiąt": "eighty",
  "osoba - osoba": "person - person",
  "osobno": "separately",
  "ostatni dzień": "last day",
  "ostatnie jest we wrzśniu": "the last one is in September",
  "ostatnio oglądaliśmy": "we recently watched",
  "owce": "sheep",
  "pada deszcz": "it's raining",
  "padał deszcz": "it rained",
  "page 93": "page 93",
  "pamiętać": "remember",
  "papierosy": "cigarettes",
  "para": "couple",
  "park - w parku": "park - in the park",
  "parking - na parkingu": "parking - in the parking lot",
  "parku": "park",
  "partner": "partner",
  "partnerka": "partner",
  "patrzeć": "look",
  "pensjonat": "Guesthouse",
  "piec": "five",
  "piec- to bake": "bake to bake",
  "piekny": "beautiful",
  "pieniędzy": "money",
  "pierogi": "Pierogi",
  "pierogi ruskie": "dumplings",
  "pierwsza książka": "first book",
  "pierwsza książka, którą sprzedaję": "the first book I sell",
  "pierwszy raz jesteśmy w tym domku": "it's our first time in this house",
  "pieszo": "on foot",
  "pisanie": "writing",
  "pisarz": "writer",
  "pisać": "to write",
  "pisać - ja piszę": "write - I write",
  "piszę w nocy": "I write at night",
  "piwne oczy": "Brown eyes",
  "piłka nożna": "football",
  "plaża": "beach",
  "please confirm the lesson :)": "please confirm the lesson :)",
  "po baskijsku": "in Basque",
  "po drugiej stronie": "on the other side",
  "po węgiersku": "in Hungarian",
  "pochmurno": "cloudy",
  "pociagiem": "by train",
  "pociagiem jest drogo": "the train is expensive",
  "pociąg jest bezpieczny": "the train is safe",
  "pocić się": "sweat",
  "podczas wojny": "during the war",
  "podjąć decyzję": "decide",
  "podobne zainteresowania": "similar interests",
  "podobni": "similar",
  "podróżować": "to travel",
  "pogoda": "weather",
  "pogoda była dobra": "weather was good",
  "pojechaliśmy": "we went",
  "pojechaliśmy do restauracji": "we went to the restaurant",
  "pole golfowe": "golf course",
  "polecieliśmy samolotem": "we went by plane",
  "policja, franzuzi lubią przemoc": "the police, the French like violence",
  "polką": "shelf",
  "pomidorowa": "tomato",
  "poniedziałek": "Monday",
  "poprawić": "to correct",
  "pora roku": "season",
  "porozmawiać o jej partnerze": "talk about her partner",
  "posprzatac dom": "clean the house",
  "poszedłem na spacer": "I went for a walk",
  "poszedłem spać o północy": "I went to bed at midnight",
  "poszliśmy": "we went",
  "poszło mi dobrze": "it went well",
  "potem": "later",
  "potem mam więcej spotkań": "then I have more meetings",
  "potrzebowałem pracy": "I needed a job",
  "potrzebuję maila od edytorki": "I need an email from the editor",
  "powieści": "novels",
  "powoli": "slowly",
  "poza domem": "outside the home",
  "poznać - get to know": "get to know",
  "poznać nowych ludzi": "meet new people",
  "poł milona": "half a million",
  "południe": "south",
  "południowym - zachodzie": "south-west",
  "pożyczać": "borrow",
  "praca administracyjna": "administrative work",
  "praca biurowa": "paperwork",
  "praca zdalna": "remote work",
  "pracowałem": "I was working",
  "pracowałem w domu": "I worked at home",
  "pracowity": "hard-working",
  "pracownik": "employee",
  "pracujesz od 9 do 16?": "do you work from 9am to 4pm?",
  "pracuję": "He's working",
  "pracuję śpię": "I work, I sleep",
  "pralka": "washing machine",
  "pralka- prać": "washing machine - wash",
  "pralki": "washing machines",
  "pralnia samoobsługowa": "launderette",
  "prasować": "iron",
  "prawo": "law",
  "preferować - woleć": "prefer - prefer",
  "prezenterem,": "presenter,",
  "procent": "percent",
  "prognoza pogody": "weather forecast",
  "program telewizyjny": "TV program",
  "programistką": "programmer",
  "programistą": "programmer",
  "programować": "program",
  "prom": "ferry",
  "proste": "easy",
  "proszę wodę": "water please",
  "prowadzić / kierować": "lead / direct",
  "prowadzić warsztaty": "Lead workshops",
  "przeciwsłoneczne": "sunscreen",
  "przeciętnego wzrostu": "average height",
  "przeciętny": "average",
  "przede wszystkim czarny": "mainly black",
  "przekąski": "snacks",
  "przepadam za": "I love it",
  "przeprowadzić się": "move",
  "przerażające": "terrifying",
  "przez 14 lat lubiłem ....": "for 14 years I liked....",
  "przez 4 lata": "for 4 years",
  "przez trzy lata nie piłem": "I didn't drink for three years",
  "przeziębiony": "has a cold",
  "przygotować się": "prepare",
  "przygotować śniadanie/ robić śniadanie": "prepare breakfast/make breakfast",
  "przyjaciel": "friend",
  "przyjaciółk": "friend",
  "przyjaciółka": "friend",
  "przyjaciółka ma urodziny": "it's a friend's birthday",
  "przyjaciółką Ewą": "friend Ewa",
  "przypadek": "case",
  "przystanek - na przystanku": "bus stop - at the bus stop",
  "przywieźć - to drive sb": "bring - to drive sb",
  "próbowałem": "I tried",
  "prąd": "current",
  "publikować": "publish",
  "purins": "purins",
  "pół etatu": "part-time job",
  "półbuty": "shoes",
  "północ": "midnight",
  "pączek": "donut",
  "płaci lepiej": "pays better",
  "płatki śniadaniowe": "breakfast cereals",
  "pływają": "they swim",
  "pływać": "to swim",
  "rano śpię": "I sleep in the morning",
  "raz na rok": "once a year",
  "raz na trzy miesiące": "once for three months",
  "raz w miesiącu": "once a month",
  "raz w tygodniu": "once a week",
  "razem": "Together",
  "recenzja muzyczna": "music review",
  "relaksować się": "to relax",
  "remont": "renovation",
  "restauracja": "restaurant",
  "restauracja wegańska": "vegan restaurant",
  "restauracjia- w restauracji": "restaurant - in a restaurant",
  "robiliśmy": "we did",
  "robić coś od zera": "making something from scratch",
  "robić zakupy": "shop",
  "robiłem stronę internetową": "I was making a website",
  "rodzeństwo": "siblings",
  "rodzice": "parents",
  "rodzina": "family",
  "rodzina- rodzice - rodzeństwo": "family - parents - siblings",
  "rok temu": "a year ago",
  "rok temu wygrała Ukraina": "Ukraine won last year",
  "rolnik": "farmer",
  "rower": "bicycle",
  "rower jest zepsuty": "the bike is broken",
  "rozmawiać": "to talk",
  "rozmawiać przez telefon": "talk on the phone",
  "rozmawiałem": "I talked",
  "rozmowa o pracę": "job interview",
  "rozmowy o pracę": "job interviews",
  "rozwiedziony/ a": "divorced",
  "rozwieść się": "get divorced",
  "rozwód": "divorce",
  "rośliny": "plants",
  "rysować": "to draw",
  "rzeka - w rzece": "river - in the river",
  "róże": "Roses",
  "salon fryzjerski": "hair salon",
  "samochód": "car",
  "samolot pasażerski": "plane",
  "samouk": "autodidact",
  "sandały": "sandals",
  "sarkastyczna": "sarcastic",
  "seniorka": "senior",
  "serial": "series",
  "seriale komediowe": "comedy series",
  "sernik": "cheesecake",
  "sery": "cheeses",
  "sezon": "season",
  "siedziałem": "I was sitting",
  "siedzieć w fotelu": "sit in a chair",
  "siedzisz w domu": "you're sitting at home",
  "sierść": "hair",
  "silna": "strong",
  "silnik": "engine",
  "silny akcent": "strong accent",
  "siostrzenica": "niece",
  "siostrzenica, siostrzenica": "niece, niece",
  "siostrzeniec": "nephew",
  "siódmego lipca": "July seventh",
  "siła- siłownia": "strength - gym",
  "siłownia": "gym",
  "skarpetki w paski": "striped socks",
  "sklep": "store",
  "sklep jubilerski": "jewelry store",
  "sklep kosmetyczny - drogeria": "cosmetics store - drugstore",
  "sklep nazywa się Polskie smaki": "the shop is called Polish Flavors",
  "sklep obuwniczy": "shoe shop",
  "skomplikowane": "complicated",
  "skończyć": "end",
  "skończyłem pracę": "I have finished my work",
  "skończyłeś pracę": "you finished work",
  "skrzynka elektryczna": "electrical box",
  "smaczny": "tasty",
  "smażyć": "to fry",
  "smutny": "sad",
  "sofa - na sofie": "sofa - on the sofa",
  "spacerowaliśmy": "We walked",
  "spacerowaliśmy długo": "we walked for a long time",
  "spacerować": "walk",
  "spacerowałem": "I was walking",
  "spacerujemy": "we walk",
  "spacerują": "they are walking",
  "spaceruję po plaży": "I'm walking on the beach",
  "spadać": "fall",
  "spać - too sleep": "sleep - too sleep",
  "spać dobrze": "sleep well",
  "spałem": "I was sleeping",
  "spektakl był odwołany": "the show was canceled",
  "spocony": "sweaty",
  "spodnie": "Pants",
  "spokojne": "calm",
  "spotkaliśmy się na ulicy": "we met on the street",
  "spotkania z ludźmi": "meeting people",
  "spotkanie": "meeting",
  "spotykam się z moim przyajcielem": "I'm meeting my friend",
  "spotykamy się z wieloma osobami": "we meet a lot of people",
  "spotykasz się z kolegami przed Świetami": "you meet your friends before Christmas",
  "spotykać": "meet",
  "spotykać się - to meet": "to meet - to meet",
  "społeczeństwo": "society",
  "spragniony": "thirsty",
  "sprawdziłem prąd": "I checked the current",
  "sprzedaję": "sell",
  "sprzedawać": "sell",
  "sprzedawczyni": "saleswoman",
  "sprzedać": "sell",
  "spróbowaliśmy iść do teatru": "we tried going to the theater",
  "spłacić": "to pay off",
  "stacja": "station",
  "stacja kolejowa": "railway station",
  "stadion - na stadionie": "stadium - at the stadium",
  "stan cywilny": "marital status",
  "starsi ludzie": "older people",
  "starsza": "older",
  "starzy": "old",
  "starówki w Anglii nie zostały zrekonstruowane": "old towns in England have not been reconstructed",
  "stodoła - stajnia": "barn - stable",
  "straszny dla siebie": "terrible for yourself",
  "strona": "side",
  "studentka, dentystka, lekarka": "student, dentist, doctor",
  "studiowałem": "I studied",
  "studiowałem teologię": "I studied theology",
  "styl": "style",
  "styl gotycki": "gothic style",
  "sukienka w kwiaty": "flower dress",
  "supermarket - w supermarkecie": "supermarket - in the supermarket",
  "synagoga - w synagodze": "synagogue - in the synagogue",
  "szanować jego decyzję": "respect his decision",
  "szczotka- szczoteczka do zębów": "brush - toothbrush",
  "szczupły": "slim",
  "szczęśliwy": "happy",
  "szkoła - w szkole": "school - at school",
  "szkoła podstawowa": "primary school",
  "szkoła- w szkole": "school- at school",
  "szpitalu": "hospital",
  "sztukę": "art",
  "szyja": "neck",
  "słodycze": "sweets",
  "słonecznie": "sunny",
  "słowo - słowa": "word - words",
  "słowo- słowa": "word-words",
  "słońce": "sun",
  "słynny kucharz": "famous chef",
  "ta koszulka": "this t-shirt",
  "tak sobie": "Not great",
  "tak szybko jak to możliwe": "as soon as possible",
  "tam było ciepło": "it was warm there",
  "tam są polskie produkty": "there are Polish products",
  "tam tu": "there here",
  "tani- taniej": "cheap-cheaper",
  "taniec": "dance",
  "tata": "dad",
  "technik": "technician",
  "tekst": "text",
  "telewior": "TV",
  "telewizja": "TV",
  "telewizor": "TV set",
  "tenisówki": "trainers",
  "teologię": "theology",
  "teraz jest listopad": "it's November now",
  "teraz nie dużo": "not much now",
  "teraz wolisz pociąg": "now you prefer the train",
  "to był weekend": "it was the weekend",
  "to było małe miasto": "it was a small town",
  "to było późno": "it was late",
  "to czternastej": "it's four o'clock",
  "to drogie": "it's expensive",
  "to duża ma dużo przyjaciół": "the big one has a lot of friends",
  "to jest dla niej trudne": "this is hard for her",
  "to jest domek": "this is a cottage",
  "to jest jedno z miejsc": "this is one of the places",
  "to jest najlepsze": "this is the best",
  "to jest praca zdalna": "this is remote work",
  "to jest trudne": "this is difficult",
  "to jest wioska": "this is a village",
  "to nie był dobry serial": "it wasn't a good series",
  "to nie była spontaniczna wizyta": "it wasn't a spontaneous visit",
  "to nie jest praca dla pieniędzy": "this is not a job for money",
  "to są dobre pieniądze": "this is good money",
  "to tanie linie lotnicze": "are low-cost airlines",
  "to wszystko": "that's all",
  "to zależy od tego co robię": "it depends on what I'm doing",
  "towarzyski": "sociable",
  "troche padał descz": "it was raining a little",
  "trochę padał deszcz": "it was raining a bit",
  "trochę pracuje": "I work a little",
  "trudno powiedzieć": "hard to say",
  "trudny do zrozumienia": "difficult to understand",
  "trzeba czekać na lotnisku": "you have to wait at the airport",
  "trzy lata": "three years",
  "trzydzieści": "thirty",
  "trzynastej": "thirteenth",
  "tu jest zima": "it's winter here",
  "tu nie ma ludzi": "there are no people here",
  "tu padał śnieg": "it was snowing here",
  "tulipany": "tulips",
  "tutaj bardzo pada śnieg": "it snows a lot here",
  "ty - cię - ciebie": "you - you - you",
  "ty boisz się": "you are afraid",
  "ty byłeś, byłaś": "you were, you were",
  "ty edytujesz": "you edit",
  "ty grasz dla przyjemności": "you play for fun",
  "ty idziesz": "you go",
  "ty interesujesz się komputerami": "you are interested in computers",
  "ty lubisz rozmawiać o piosenkach": "you like talking about songs",
  "ty nie masz telewizji": "you don't have TV",
  "ty nie miałeś problemu z lataniem": "you had no problem with flying",
  "ty wolisz": "you prefer",
  "ty śpisz": "you are sleeping",
  "tydzień": "week",
  "tydzień temu": "a week ago",
  "tyle samo godzin": "the same number of hours",
  "tylko ja z Agatą": "only me and Agata",
  "tylko jedna rozmowa": "just one conversation",
  "tym sensie": "in this sense",
  "tłuste": "fat",
  "ubierać się - ja ubieram się": "get dressed - I get dressed",
  "ubranie": "clothes",
  "uczę się robić pierogi": "I'm learning to make dumplings",
  "ulubiony dzień tygodnia": "favorite day of the week",
  "umrzeć - to die": "to die is to die",
  "umówię panią na wizytę o 20": "I'll make an appointment for you at 8 p.m",
  "uprawiają sport": "do sport",
  "uprawiać sport": "to do sports",
  "urlop": "vacation",
  "urodziny": "birthday",
  "utalentowany muzycznie": "musically talented",
  "użyteczne": "useful",
  "użyteczny prezent": "useful gift",
  "w 2 tygodnie": "in 2 weeks",
  "w Anglii": "in England",
  "w Anglii 3 lata temu": "in England 3 years ago",
  "w Anglii to jest daleko": "in England it's far away",
  "w Briatolu": "in Briatol",
  "w Londynie": "in London",
  "w Paryżu": "in Paris",
  "w Stanach Zjednoczonych": "in United States",
  "w Szkocji": "in Scotland",
  "w aptece": "at the pharmacy",
  "w banku": "in the bank",
  "w barze": "at the bar",
  "w basenie": "in the swimming pool",
  "w bibliotece": "in the library",
  "w biurze": "in the office",
  "w bloku": "in a block of flats",
  "w centrum": "in the center",
  "w czasie mojej pracy": "during my work",
  "w czerwcu": "in June",
  "w domu": "At home",
  "w drugą ulicę": "to the other street",
  "w firmie , która produkowała alkohol": "in a company that produced alcohol",
  "w galerii handlowej": "in a shopping mall",
  "w galerii sztuki": "in the art gallery",
  "w górach": "in the mountains",
  "w ich domu": "In their house",
  "w innym mieście": "in another city",
  "w internecie": "online",
  "w kawiarnii": "in the cafe",
  "w każdym sezonie jest inne menu": "each season has a different menu",
  "w kinie": "in the cinema",
  "w kraju islamskim": "in an Islamic country",
  "w krakowie trębacz gra hejnał na trąbce": "in Krakow, a trumpeter plays the bugle call on the trumpet",
  "w księgarnii": "in the bookstore",
  "w mieszkaniu": "in the apartment",
  "w mieście": "in the city",
  "w moim wieku": "at my age",
  "w mojej firmie": "in my company",
  "w muzeum": "in museum",
  "w organizacji charytatywnej": "in a charity organization",
  "w pałacu": "in the palace",
  "w piątek": "on Friday",
  "w pracy": "At work",
  "w przyszłośći": "in the future",
  "w przyszłym tygodniu": "next week",
  "w różnych miejscach": "in different places",
  "w salonie fryzjerskim": "in a hairdressing salon",
  "w samochodzie": "in the car",
  "w sobotę": "on Saturday",
  "w statystyce": "in statistics",
  "w supermarkecie": "in the supermarket",
  "w szkole": "at school",
  "w szkole podstawowej": "in primary school",
  "w teatrze": "In the theatre",
  "w tej firmie": "in this company",
  "w twoim wiku": "at your age",
  "w tym mieszkaniu": "in this flat",
  "w tym tygodniu idziesz do biura": "You're going to the office this week",
  "w warsztacie samochodowym": "in a car repair shop",
  "w wersji papierowej": "in paper version",
  "w zimie": "in winter",
  "w zimie jest silny wiatr": "there is a strong wind in winter",
  "w środy": "on Wednesdays",
  "warsztat": "workshop",
  "warsztaty": "workshops",
  "wałek": "roller",
  "wcale": "at all",
  "wczesnie wstawać": "to get up early",
  "wcześnie- późno": "early late",
  "wcześniej": "before",
  "wczoraj": "Yesterday",
  "wczoraj byliśmy z kotem u weterynarza": "Yesterday we went to the vet with our cat",
  "wczoraj padał śnieg": "it was snowing yesterday",
  "wczoraj za ciepło": "yesterday too warm",
  "wdowa": "widow",
  "wdowa/ wdowiec": "widow/widower",
  "wdowiec": "widower",
  "we wrześniu": "in September",
  "wejście": "entry",
  "wesoły": "cheerful",
  "wiadomości": "the news",
  "widoki": "views",
  "widzieliśmy się z przyjaciółmi": "we saw friends",
  "widzieć": "see",
  "wieczorami": "in the evenings",
  "wiedzieć": "know",
  "wietrznie": "windy",
  "wieś - wioska": "village - village",
  "wioska": "village",
  "wiosna": "spring",
  "więc nie wiem": "so I do not know",
  "więcej muzykę i literaturę": "more music and literature",
  "więcej mężczyzn niż kobiet": "more men than women",
  "więcej niż 10 lat": "more than 10 years",
  "woleć": "prefer",
  "wolę": "I prefer",
  "wróciliśmy w niedzielę pociągiem": "we returned on Sunday by train",
  "wrócić": "come back",
  "wrócić - come back": "come back - come back",
  "wschód": "east",
  "wschód, zachód": "East West",
  "współczesny angielski": "modern English",
  "wstawać - ja wstaję": "get up - I get up",
  "wstawać - to get up": "to get up - to get up",
  "wszystko dobrze": "All good",
  "wy boicie się": "you are afraid",
  "wy się znacie ale wy nie lubicie się bardzo": "you know each other but you don't like each other very much",
  "wy wolicie": "you prefer",
  "wy śpicie": "you are sleeping",
  "wybrać - to choose": "to choose - to choose",
  "wychodzić z domu": "go out",
  "wydawca": "publisher",
  "wygodnie": "comfortably",
  "wyjście": "Exit",
  "wyjść z domu": "leave the house",
  "wykonywałem pracę administracyjną": "I did administrative work",
  "wynagrodzenie": "remuneration",
  "wynajmują ten domek": "they are renting this house",
  "wyniki": "results",
  "wypadek": "accident",
  "wyraźnie": "clearly",
  "wysoki": "tall",
  "wyspa": "island",
  "wystawa": "exhibition",
  "wywiad": "interview",
  "wyłączyć": "turn off",
  "wzgórza": "hills",
  "wózek": "cart",
  "włosy": "hair",
  "włączyć": "to turn on",
  "z Agatą": "with Agata",
  "z Londynu": "from London",
  "z cukrem": "with sugar",
  "z dwutysięcznego drugiego roku": "from the year two thousand and two",
  "z dzieciństwa": "from childhood",
  "z kim byłem": "who I was with",
  "z kolegami": "with colleagues",
  "z kotami": "with cats",
  "z lekarzem": "with a doctor",
  "z lektorem": "with a voice-over",
  "z moim kolegą": "with my friend",
  "z moimi przyjaciółkami": "with my friends",
  "z moimi przyjaciółmi": "with my friends",
  "z moją przyjaciółką": "with my friend",
  "z moją rodziną": "with my family",
  "z ogórkiem": "with cucumber",
  "z pracy": "from work",
  "z pracą": "with work",
  "z przyjacielem": "with a friend",
  "z przyjaciółkami": "with friends",
  "z przyjaciółką": "with a friend",
  "z przyjaciółmi": "with friends",
  "z psem": "with a dog",
  "z rybą": "with fish",
  "z solą": "with salt",
  "z zębami": "with teeth",
  "za 2 tygodnie": "in 2 weeks",
  "za darmo": "for free",
  "za miesiąc": "in a month",
  "za muzykę którą ja gram": "for the music I play",
  "za tydzień": "next week",
  "za zimno": "too cold",
  "zabawna": "funny",
  "zabrać - brać": "take - take",
  "zachód": "West",
  "zaczałem pracę o": "I started working at",
  "zaczynać pracę": "start work",
  "zacząlem grać na instrumencie": "I started playing an instrument",
  "zacząłeś": "you started",
  "zadanie - zadania": "task - tasks",
  "zadowoleni": "satisfied",
  "zainteresowania": "interests",
  "zajmować dużo czasu": "take a lot of time",
  "zajmować sie - to take care of": "to take care of",
  "zakupy": "shopping",
  "zamawiamy": "we order",
  "zamawiać": "order",
  "zapomnieć - to forget": "forget - to forget",
  "zapraszać do domum": "invite you home",
  "zaprosić": "invite",
  "zarabiać": "to earn",
  "zasada- zasady": "principle- principles",
  "zawodowy": "professional",
  "zawsze": "Always",
  "zbierać": "collect",
  "zbierać podpisy": "collect signatures",
  "zdenerwowany": "upset",
  "zdrowy": "healthy",
  "ze mną": "with me",
  "zestresowany": "stressed",
  "zi": "zi",
  "ziemniaki": "potatoes",
  "zima": "Winter",
  "zimno": "Cold",
  "zmienić plany": "change plans",
  "zmienić pracę": "To change job",
  "zmienił się czas": "time has changed",
  "zmywać naczynia": "wash the dishes",
  "zmęczona": "tired",
  "zmęczony": "tired",
  "znajomi": "friends",
  "zniżka": "discount",
  "znudzone": "bored",
  "zobaczyć": "see",
  "zorganizowany": "organized",
  "zostaćw domu": "stay at home",
  "zrobił się ciemny": "it turned dark",
  "zwiedzałam": "I was sightseeing",
  "zwierzęta": "Animals",
  "zwolnienie": "sick leave",
  "złe wspomnienia": "bad memories",
  "zły": "bad",
  "ćwiczenie 2/ 96": "exercise 2/ 96",
  "ćwiczyć": "practice",
  "łatwiejsze": "easier",
  "łazienka - w łazience": "bathroom - in the bathroom",
  "łódź": "Łódź",
  "łóżko - w łóżku": "bed - in bed",
  "Święta": "Holidays",
  "ślub": "wedding",
  "śniadanie": "breakfast",
  "śnieg nie pada każdego roku": "it doesn't snow every year",
  "śpiewa": "sing",
  "śpię i pracuję": "I sleep and work",
  "środa - środek": "Wednesday - middle",
  "święto narodowe": "National Day",
  "źle": "Badly",
  "źle zorganizowany": "poorly organized",
  "żart": "joke",
  "że oni podejmą decyzję szybko": "that they will make a decision quickly",
  "że zdecydują szybko": "that they will decide quickly",
  "żeby być nauczycielką": "to be a teacher",
  "żeby uczyć się polskiego": "to learn Polish",
  "żebym skończył zadanie": "for me to finish the task",
  "żonaty": "married",
  "żyć - on nie żyje": "live - he is dead",
  "😅 super, za tydzień mi opowiesz": "😅 great, you'll tell me in a week"
}
